ndeftool/__init__.py
ndeftool/cli.py
ndeftool/commands/IDentifier.py
ndeftool/commands/Load.py
ndeftool/commands/PayLoad.py
ndeftool/commands/Print.py
ndeftool/commands/SMartPoster.py
ndeftool/commands/Save.py
ndeftool/commands/TeXT.py
ndeftool/commands/TypeName.py
ndeftool/commands/URI.py
ndeftool/commands/__init__.py
ndeftool-0.1.3.dist-info/LICENSE
ndeftool-0.1.3.dist-info/METADATA
ndeftool-0.1.3.dist-info/WHEEL
ndeftool-0.1.3.dist-info/entry_points.txt
ndeftool-0.1.3.dist-info/top_level.txt
ndeftool-0.1.3.dist-info/RECORD
