Metadata-Version: 2.1
Name: ndeftool
Version: 0.1.3
Summary: Create or inspect NFC Data Exchange Format messages.
Home-page: https://github.com/nfcpy/ndeftool/
Author: Stephen Tiedemann
Author-email: stephen.tiedemann@gmail.com
Maintainer: Stephen Tiedemann
Maintainer-email: stephen.tiedemann@gmail.com
License: ISC
Keywords: ndef,nfc
Classifier: Development Status :: 5 - Production/Stable
Classifier: Intended Audience :: Developers
Classifier: Natural Language :: English
Classifier: License :: OSI Approved :: ISC License (ISCL)
Classifier: Operating System :: OS Independent
Classifier: Programming Language :: Python
Classifier: Programming Language :: Python :: 2
Classifier: Programming Language :: Python :: 2.7
Classifier: Programming Language :: Python :: 3
Classifier: Programming Language :: Python :: 3.4
Classifier: Programming Language :: Python :: 3.5
Classifier: Programming Language :: Python :: Implementation :: CPython
Classifier: Programming Language :: Python :: Implementation :: PyPy
Classifier: Topic :: Software Development :: Libraries :: Python Modules
License-File: LICENSE
Requires-Dist: ndeflib
Requires-Dist: click
Requires-Dist: python-magic
